pytorch_sidu/__init__.py
pytorch_sidu/sidu.py
pytorch_sidu/utils/utils.py
pytorch_sidu-1.1.3.dist-info/LICENSE
pytorch_sidu-1.1.3.dist-info/METADATA
pytorch_sidu-1.1.3.dist-info/WHEEL
pytorch_sidu-1.1.3.dist-info/top_level.txt
pytorch_sidu-1.1.3.dist-info/RECORD
