Metadata-Version: 2.1
Name: pytorch-sidu
Version: 1.1.3
Summary: SIDU: SImilarity Difference and Uniqueness method for explainable AI
Home-page: https://github.com/MarcoParola/pytorch-sidu
Author: Marco Parola
Author-email: marcoparola96@gmail.com
Classifier: Programming Language :: Python :: 3
Classifier: License :: OSI Approved :: GNU General Public License v3 (GPLv3)
Classifier: Operating System :: OS Independent
Classifier: Development Status :: 4 - Beta
Requires-Python: >=3.6
License-File: LICENSE
Requires-Dist: torch
Requires-Dist: torchvision
Requires-Dist: numpy
